{
  "source": "Bilibili热门",
  "updated_at": "2026-04-17 01:54:19",
  "news": [
    {
      "rank": 1,
      "title": "《崩坏：星穹铁道》即兴巡演PV：「新手指南」",
      "author": "崩坏星穹铁道",
      "play_count": 3093051,
      "link": "https://b23.tv/BV1HyQ5BgEgo"
    },
    {
      "rank": 2,
      "title": "郝 哥 不 在",
      "author": "岩罗Crv",
      "play_count": 1829020,
      "link": "https://b23.tv/BV1RwdhBmE3M"
    },
    {
      "rank": 3,
      "title": "终于来了！大疆Pocket 4上手",
      "author": "影视飓风",
      "play_count": 1185357,
      "link": "https://b23.tv/BV1DgdhBGEq2"
    },
    {
      "rank": 4,
      "title": "短片《榜样》·致敬雷锋",
      "author": "编导李让",
      "play_count": 4224302,
      "link": "https://b23.tv/BV1p7QeB8EeZ"
    },
    {
      "rank": 5,
      "title": "《物理兴奋剂》",
      "author": "伤心欲茄222",
      "play_count": 3139773,
      "link": "https://b23.tv/BV1ZxQpBsEuN"
    },
    {
      "rank": 6,
      "title": "凭实力单身",
      "author": "三金啊GC",
      "play_count": 3753700,
      "link": "https://b23.tv/BV1X2Q4B4EK5"
    },
    {
      "rank": 7,
      "title": "一个人如果一辈子都在玩游戏，会留下什么？",
      "author": "给我来个币Arcade",
      "play_count": 1845864,
      "link": "https://b23.tv/BV14fQ4BEEWd"
    },
    {
      "rank": 8,
      "title": "和李现，攀登人生第一座雪山",
      "author": "Linksphotograph",
      "play_count": 1544169,
      "link": "https://b23.tv/BV1SSQLBREVV"
    },
    {
      "rank": 9,
      "title": "印度指定有点说法",
      "author": "燕三嘤嘤嘤",
      "play_count": 2475185,
      "link": "https://b23.tv/BV1sHQ7BXE1X"
    },
    {
      "rank": 10,
      "title": "盘点嘎子直播带货名场面！经典战役卖酸奶居然还不是最离谱的？！哈哈哈哈",
      "author": "文西与阿漆",
      "play_count": 2545081,
      "link": "https://b23.tv/BV1usQvByEJS"
    }
  ]
}